gitlab_evaluate/__init__.py
gitlab_evaluate/docs/quick-start_docker.md
gitlab_evaluate/lib/__init__.py
gitlab_evaluate/lib/api_models/application_stats.py
gitlab_evaluate/lib/api_models/user.py
gitlab_evaluate/lib/cmd.py
gitlab_evaluate/lib/db_utils.py
gitlab_evaluate/lib/filetree.py
gitlab_evaluate/lib/git.py
gitlab_evaluate/lib/log_utils.py
gitlab_evaluate/lib/utils.py
gitlab_evaluate/main.py
gitlab_evaluate/migration_readiness/__init__.py
gitlab_evaluate/migration_readiness/ado/__init__.py
gitlab_evaluate/migration_readiness/ado/evaluate.py
gitlab_evaluate/migration_readiness/ado/feed_worker.py
gitlab_evaluate/migration_readiness/ado/report_generator.py
gitlab_evaluate/migration_readiness/bitbucket/__init__.py
gitlab_evaluate/migration_readiness/bitbucket/evaluate.py
gitlab_evaluate/migration_readiness/bitbucket/report_generator.py
gitlab_evaluate/migration_readiness/github_enterprise/__init__.py
gitlab_evaluate/migration_readiness/github_enterprise/evaluate.py
gitlab_evaluate/migration_readiness/github_enterprise/report_generator.py
gitlab_evaluate/migration_readiness/gitlab/__init__.py
gitlab_evaluate/migration_readiness/gitlab/constants.py
gitlab_evaluate/migration_readiness/gitlab/data_classes/project.py
gitlab_evaluate/migration_readiness/gitlab/evaluate.py
gitlab_evaluate/migration_readiness/gitlab/flag_remediation.py
gitlab_evaluate/migration_readiness/gitlab/limits.py
gitlab_evaluate/migration_readiness/gitlab/queries.py
gitlab_evaluate/migration_readiness/gitlab/report_generator.py
gitlab_evaluate/migration_readiness/jenkins/__init__.py
gitlab_evaluate/migration_readiness/jenkins/auto_encoder.py
gitlab_evaluate/migration_readiness/jenkins/data_classes/job.py
gitlab_evaluate/migration_readiness/jenkins/data_classes/plugin.py
gitlab_evaluate/migration_readiness/jenkins/evaluate.py
gitlab_evaluate/migration_readiness/jenkins/groovy_converter.py
gitlab_evaluate/migration_readiness/jenkins/jenkins.py
gitlab_evaluate-0.41.0.dist-info/METADATA
gitlab_evaluate-0.41.0.dist-info/WHEEL
gitlab_evaluate-0.41.0.dist-info/entry_points.txt
gitlab_evaluate-0.41.0.dist-info/licenses/LICENSE
gitlab_evaluate-0.41.0.dist-info/RECORD
