Metadata-Version: 2.4
Name: gitlab_evaluate
Version: 0.41.0
Summary: Scans GitLab instance and ranks projects against a set of criteria. Can be used to identiy projects that may have too much metadata/size to reliably export or import.
License: MIT
License-File: LICENSE
Author: GitLab Professional Services
Author-email: proserv@gitlab.com
Requires-Python: >=3.11,<=3.14
Classifier: License :: OSI Approved :: MIT License
Classifier: Programming Language :: Python :: 3
Classifier: Programming Language :: Python :: 3.11
Classifier: Programming Language :: Python :: 3.12
Classifier: Programming Language :: Python :: 3.13
Classifier: Programming Language :: Python :: 3.14
Requires-Dist: PyYAML (>=6.0,<7.0)
Requires-Dist: click (>=8.1.7,<9.0.0)
Requires-Dist: dacite (>=1.8.1,<2.0.0)
Requires-Dist: gitlab-ps-utils (>=0.16.0,<0.17.0)
Requires-Dist: numpy (>=2.0.0,<3.0.0)
Requires-Dist: pydantic (>=1.8.2,<2.0.0)
Requires-Dist: python-dateutil (>=2.9.0.post0,<3.0.0)
Requires-Dist: python-jenkins (>=1.8.2,<2.0.0)
Requires-Dist: requests (>=2.32.0,<3.0.0)
Requires-Dist: scikit-learn (>=1.5.0,<2.0.0)
Requires-Dist: torch (>=2.3.0)
Requires-Dist: torchvision (>=0.18.0)
Requires-Dist: xlsxwriter (>=3.1.2,<4.0.0)
Project-URL: Homepage, https://gitlab.com/gitlab-org/professional-services-automation/tools/utilities/evaluate
